eventflit/__init__.py
eventflit/aiohttp.py
eventflit/authentication_client.py
eventflit/cacert.pem
eventflit/client.py
eventflit/errors.py
eventflit/eventflit.py
eventflit/eventflit_client.py
eventflit/gae.py
eventflit/http.py
eventflit/notification_client.py
eventflit/requests.py
eventflit/signature.py
eventflit/tornado.py
eventflit/util.py
eventflit/version.py
eventflit-0.1.0.dist-info/DESCRIPTION.rst
eventflit-0.1.0.dist-info/METADATA
eventflit-0.1.0.dist-info/RECORD
eventflit-0.1.0.dist-info/WHEEL
eventflit-0.1.0.dist-info/metadata.json
eventflit-0.1.0.dist-info/top_level.txt
